functionapprest/__init__.py
functionapprest/__version__.py
functionapprest-0.0.1.dist-info/LICENSE
functionapprest-0.0.1.dist-info/METADATA
functionapprest-0.0.1.dist-info/WHEEL
functionapprest-0.0.1.dist-info/top_level.txt
functionapprest-0.0.1.dist-info/RECORD
