Metadata-Version: 2.1
Name: functionapprest
Version: 0.0.1
Summary: Micro framework for azure functions with optional json schema validation
Home-page: https://github.com/eduardomourar/python-functionapprest
Author: eduardomourar
Author-email: eduardo_demoura@yahoo.com.br
License: UNKNOWN
Keywords: functionapp azure rest json schema jsonschema
Platform: UNKNOWN
Classifier: Development Status :: 2 - Pre-Alpha
Classifier: Intended Audience :: Developers
Classifier: Natural Language :: English
Classifier: Programming Language :: Python :: 2.7
Classifier: Programming Language :: Python :: 3.4
Classifier: Programming Language :: Python :: 3.5
Classifier: Programming Language :: Python :: 3.6
Requires-Dist: jsonschema (>=2.5.1)
Requires-Dist: strict-rfc3339 (>=0.7)
Requires-Dist: azure-functions (==1.0.0b3)
Requires-Dist: werkzeug (>=0.14.1)
Provides-Extra: test
Requires-Dist: coverage (==4.1) ; extra == 'test'
Requires-Dist: pyyaml (==4.2b4) ; extra == 'test'
Requires-Dist: pytest (==2.9.2) ; extra == 'test'
Requires-Dist: mock (>=2.0.0) ; extra == 'test'
Requires-Dist: prospector (==1.1.6.2) ; extra == 'test'
Requires-Dist: jsonschema (>=2.5.1) ; extra == 'test'
Requires-Dist: strict-rfc3339 (>=0.7) ; extra == 'test'
Requires-Dist: azure-functions (==1.0.0b3) ; extra == 'test'
Requires-Dist: werkzeug (>=0.14.1) ; extra == 'test'
